vr180_convert/__init__.py
vr180_convert/__main__.py
vr180_convert/cli.py
vr180_convert/py.typed
vr180_convert/remapper.py
vr180_convert/testing.py
vr180_convert/transformer.py
vr180_convert-0.6.2.dist-info/LICENSE
vr180_convert-0.6.2.dist-info/METADATA
vr180_convert-0.6.2.dist-info/WHEEL
vr180_convert-0.6.2.dist-info/entry_points.txt
vr180_convert-0.6.2.dist-info/RECORD
