Metadata-Version: 2.1
Name: vr180-convert
Version: 0.6.2
Summary: Simple VR180 image converter
Home-page: https://github.com/34j/vr180-convert
License: MIT
Author: 34j
Author-email: 34j.95a2p@simplelogin.com
Requires-Python: >=3.9,<4.0
Classifier: Development Status :: 2 - Pre-Alpha
Classifier: Intended Audience :: Developers
Classifier: License :: OSI Approved :: MIT License
Classifier: Natural Language :: English
Classifier: Operating System :: OS Independent
Classifier: Programming Language :: Python :: 3
Classifier: Programming Language :: Python :: 3.9
Classifier: Programming Language :: Python :: 3.10
Classifier: Programming Language :: Python :: 3.11
Classifier: Programming Language :: Python :: 3.12
Classifier: Topic :: Software Development :: Libraries
Provides-Extra: all
Provides-Extra: xmp
Requires-Dist: attrs (>=23.2.0,<24.0.0)
Requires-Dist: numpy-quaternion (>=2023.0.3,<2024.0.0)
Requires-Dist: opencv-python (>=4.9.0.80,<5.0.0.0)
Requires-Dist: python-xmp-toolkit (>=2.0.2,<3.0.0) ; extra == "xmp" or extra == "all"
Requires-Dist: rich (>=10)
Requires-Dist: scikit-learn (>=1.4.2,<2.0.0)
Requires-Dist: seaborn (>=0.13.2,<0.14.0)
Requires-Dist: strenum (>=0.4.15,<0.5.0)
Requires-Dist: typer (>=0.12.0,<0.13.0)
Project-URL: Bug Tracker, https://github.com/34j/vr180-convert/issues
Project-URL: Changelog, https://github.com/34j/vr180-convert/blob/main/CHANGELOG.md
Project-URL: Documentation, https://vr180-convert.readthedocs.io
Project-URL: Repository, https://github.com/34j/vr180-convert
